pyvger/__init__.py
pyvger/batchcat.py
pyvger/constants.py
pyvger/core.py
pyvger/exceptions.py
pyvger/helper.py
pyvger/version.py
pyvger/test/__init__.py
pyvger/test/test_core.py
pyvger-0.11.1.dist-info/METADATA
pyvger-0.11.1.dist-info/WHEEL
pyvger-0.11.1.dist-info/top_level.txt
pyvger-0.11.1.dist-info/RECORD
